ATSAPI.py
ATSAPI-0.4.dist-info/LICENSE
ATSAPI-0.4.dist-info/METADATA
ATSAPI-0.4.dist-info/WHEEL
ATSAPI-0.4.dist-info/top_level.txt
ATSAPI-0.4.dist-info/RECORD
